feconomics/__init__.py
feconomics/constants.py
feconomics/exceptions.py
feconomics/py.typed
feconomics/validation.py
feconomics/core/__init__.py
feconomics/core/banking.py
feconomics/core/cash_flow.py
feconomics/core/depreciation.py
feconomics/core/growth.py
feconomics/core/petroleum.py
feconomics/core/profitability.py
feconomics/core/risk.py
feconomics/core/time_value.py
feconomics-0.1.0.dist-info/METADATA
feconomics-0.1.0.dist-info/WHEEL
feconomics-0.1.0.dist-info/licenses/LICENSE.md
feconomics-0.1.0.dist-info/RECORD
